gitlink-0.5.0.dist-info/METADATA
gitlink-0.5.0.dist-info/metadata.json
gitlink-0.5.0.dist-info/entry_points.txt
gitlink-0.5.0.dist-info/RECORD
gitlink-0.5.0.dist-info/top_level.txt
gitlink-0.5.0.dist-info/zip-safe
gitlink-0.5.0.dist-info/WHEEL
gitlink-0.5.0.dist-info/DESCRIPTION.rst
gitlink-0.5.0.data/data/share/man/man1/git-link.1
gitlink/__main__.py
gitlink/pyperclip.py
gitlink/__init__.py
gitlink/repobrowsers.py
gitlink/main.py
gitlink/git.py
gitlink/utils.py
