Metadata-Version: 2.0
Name: gitlink
Version: 0.5.0
Summary: Git sub-command for getting a repo browser link to a git object
Home-page: https://github.com/gvalkov/git-link
Author: Georgi Valkov
Author-email: georgi.t.valkov@gmail.com
License: Revised BSD License
Keywords: git gitweb github cgit subcommand
Platform: UNKNOWN
Classifier: Environment :: Console
Classifier: Topic :: Utilities
Classifier: Operating System :: OS Independent
Classifier: Programming Language :: Python :: 2.7
Classifier: Programming Language :: Python :: 3.3
Classifier: Programming Language :: Python :: 3.4
Classifier: License :: OSI Approved :: BSD License
Classifier: Development Status :: 5 - Production/Stable
